geonames.py
geonames_lib-0.4.1.dist-info/LICENSE.md
geonames_lib-0.4.1.dist-info/METADATA
geonames_lib-0.4.1.dist-info/WHEEL
geonames_lib-0.4.1.dist-info/top_level.txt
geonames_lib-0.4.1.dist-info/RECORD
