Metadata-Version: 2.1
Name: geonames-lib
Version: 0.4.1
Summary: Library for working with GeoNames dump
Home-page: https://github.com/abmyii/geonames
Author: abmyii
Author-email: abdurrahmaaniqbal@hotmail.com
License: UNKNOWN
Platform: UNKNOWN
Classifier: Intended Audience :: Science/Research
Classifier: Intended Audience :: Developers
Classifier: License :: OSI Approved :: MIT License
Classifier: Programming Language :: Python
Classifier: Programming Language :: Python :: 3
Classifier: Programming Language :: Python :: 3.5
Classifier: Programming Language :: Python :: 3.6
Classifier: Programming Language :: Python :: 3.7
Classifier: Programming Language :: Python :: 3.8
Classifier: Topic :: Software Development
Classifier: Operating System :: POSIX
Classifier: Operating System :: Unix
Requires-Dist: fuzzywuzzy
Requires-Dist: pandas
